lagrangebench/__init__.py
lagrangebench/case_setup/__init__.py
lagrangebench/case_setup/case.py
lagrangebench/case_setup/features.py
lagrangebench/data/__init__.py
lagrangebench/data/data.py
lagrangebench/data/utils.py
lagrangebench/defaults.py
lagrangebench/evaluate/__init__.py
lagrangebench/evaluate/metrics.py
lagrangebench/evaluate/rollout.py
lagrangebench/evaluate/utils.py
lagrangebench/models/__init__.py
lagrangebench/models/base.py
lagrangebench/models/egnn.py
lagrangebench/models/gns.py
lagrangebench/models/linear.py
lagrangebench/models/painn.py
lagrangebench/models/segnn.py
lagrangebench/models/utils.py
lagrangebench/runner.py
lagrangebench/train/__init__.py
lagrangebench/train/strats.py
lagrangebench/train/trainer.py
lagrangebench/utils.py
lagrangebench-0.2.0.dist-info/LICENSE
lagrangebench-0.2.0.dist-info/METADATA
lagrangebench-0.2.0.dist-info/WHEEL
lagrangebench-0.2.0.dist-info/RECORD
