Metadata-Version: 2.1
Name: lagrangebench
Version: 0.2.0
Summary: LagrangeBench: A Lagrangian Fluid Mechanics Benchmarking Suite
Home-page: https://lagrangebench.readthedocs.io/
License: MIT
Keywords: smoothed-particle-hydrodynamics,benchmark-suite,lagrangian-dynamics,graph-neural-networks,lagrangian-particles
Author: Artur Toshev, Gianluca Galletti
Author-email: artur.toshev@tum.de
Requires-Python: >=3.9,<=3.11
Classifier: Development Status :: 3 - Alpha
Classifier: Intended Audience :: Science/Research
Classifier: License :: OSI Approved :: MIT License
Classifier: Operating System :: MacOS
Classifier: Operating System :: POSIX :: Linux
Classifier: Programming Language :: Python :: 3
Classifier: Programming Language :: Python :: 3.9
Classifier: Programming Language :: Python :: 3.10
Classifier: Programming Language :: Python :: 3.11
Classifier: Topic :: Scientific/Engineering :: Artificial Intelligence
Classifier: Topic :: Scientific/Engineering :: Hydrology
Classifier: Topic :: Scientific/Engineering :: Physics
Classifier: Topic :: Software Development :: Libraries :: Python Modules
Classifier: Typing :: Typed
Requires-Dist: PyYAML (>=6.0)
Requires-Dist: cloudpickle (>=2.2.1)
Requires-Dist: dm-haiku (>=0.0.10)
Requires-Dist: e3nn-jax (==0.20.3)
Requires-Dist: h5py (>=3.9.0)
Requires-Dist: jax-sph (>=0.0.3)
Requires-Dist: jax[cpu] (==0.4.29)
Requires-Dist: jaxlib (==0.4.29)
Requires-Dist: jmp (>=0.0.4)
Requires-Dist: jraph (==0.0.6.dev0)
Requires-Dist: matscipy (>=0.8.0)
Requires-Dist: numpy (>=1.24.4)
Requires-Dist: omegaconf (>=2.3.0)
Requires-Dist: optax (==0.1.7)
Requires-Dist: ott-jax (>=0.4.2)
Requires-Dist: pyvista (>=0.42.2)
Requires-Dist: torch (==2.3.1+cpu)
Requires-Dist: wandb (>=0.15.11)
Requires-Dist: wget (>=3.2)
Project-URL: Documentation, https://lagrangebench.readthedocs.io/
Project-URL: Repository, https://github.com/tumaer/lagrangebench
